templatey-2025.11.13.0.dist-info/METADATA
templatey-2025.11.13.0.dist-info/WHEEL
templatey-2025.11.13.0.dist-info/entry_points.txt
templatey/__init__.py
templatey/_bootstrapping.py
templatey/_error_collector.py
templatey/_fields.py
templatey/_finalizers.py
templatey/_provenance.py
templatey/_renderer.py
templatey/_signature.py
templatey/_slot_tree.py
templatey/_types.py
templatey/environments.py
templatey/exceptions.py
templatey/interpolators.py
templatey/modifiers.py
templatey/parser.py
templatey/prebaked/__init__.py
templatey/prebaked/configs.py
templatey/prebaked/env_funcs.py
templatey/prebaked/loaders.py
templatey/prebaked/template_configs.py
templatey/prebaked/verifiers.py
templatey/py.typed
templatey/templates.py
templatey-2025.11.13.0.dist-info/RECORD
