Metadata-Version: 2.1
Name: templatey
Version: 2025.11.13.0
Summary: A simple (but powerful), type-hinted templating engine
Requires-Python: >=3.12
Requires-Dist: dceiref>=2025.11.9.0
Requires-Dist: docnote>=2025.8.5.0
Requires-Dist: typing_extensions>=4.12.2
Provides-Extra: async
Requires-Dist: anyio>=4.6.2; extra == "async"
